harlequin/__init__.py
harlequin/__main__.py
harlequin/actions.py
harlequin/adapter.py
harlequin/app.py
harlequin/app.tcss
harlequin/app_base.py
harlequin/bindings.py
harlequin/cache.py
harlequin/catalog.py
harlequin/catalog_cache.py
harlequin/cli.py
harlequin/colors.py
harlequin/config.py
harlequin/config_wizard.py
harlequin/copy_formats.py
harlequin/copy_widgets.py
harlequin/driver.py
harlequin/editor_cache.py
harlequin/exception.py
harlequin/export.py
harlequin/global.tcss
harlequin/history.py
harlequin/keymap.py
harlequin/keys_app.py
harlequin/keys_app.tcss
harlequin/locale_manager.py
harlequin/messages.py
harlequin/options.py
harlequin/plugins.py
harlequin/py.typed
harlequin/transaction_mode.py
harlequin/windows_timezone.py
harlequin/autocomplete/__init__.py
harlequin/autocomplete/completers.py
harlequin/autocomplete/completion.py
harlequin/autocomplete/constants.py
harlequin/components/__init__.py
harlequin/components/code_editor.py
harlequin/components/confirm_modal.py
harlequin/components/debug_info.py
harlequin/components/error_modal.py
harlequin/components/export_screen.py
harlequin/components/help_screen.md
harlequin/components/help_screen.py
harlequin/components/history_screen.py
harlequin/components/results_viewer.py
harlequin/components/run_query_bar.py
harlequin/components/data_catalog/__init__.py
harlequin/components/data_catalog/database_tree.py
harlequin/components/data_catalog/file_tree.py
harlequin/components/data_catalog/s3_tree.py
harlequin/components/data_catalog/tree.py
harlequin_duckdb/__init__.py
harlequin_duckdb/adapter.py
harlequin_duckdb/catalog.py
harlequin_duckdb/cli_options.py
harlequin_duckdb/completions.py
harlequin_duckdb/interactions.py
harlequin_duckdb/py.typed
harlequin_sqlite/__init__.py
harlequin_sqlite/adapter.py
harlequin_sqlite/catalog.py
harlequin_sqlite/cli_options.py
harlequin_sqlite/completions.py
harlequin_sqlite/interactions.py
harlequin_sqlite/py.typed
harlequin_vscode/__init__.py
harlequin-2.5.1.dist-info/METADATA
harlequin-2.5.1.dist-info/WHEEL
harlequin-2.5.1.dist-info/entry_points.txt
harlequin-2.5.1.dist-info/licenses/LICENSE
harlequin-2.5.1.dist-info/RECORD
