Metadata-Version: 2.4
Name: harlequin
Version: 2.5.1
Summary: The SQL IDE for Your Terminal.
Project-URL: Homepage, https://harlequin.sh
Project-URL: Documentation, https://harlequin.sh/docs/getting-started/index
Project-URL: Repository, https://github.com/tconbeer/harlequin
Project-URL: Bug Tracker, https://github.com/tconbeer/harlequin/issues
Project-URL: Changelog, https://github.com/tconbeer/harlequin/blob/main/CHANGELOG.md
Author-email: Ted Conbeer <tconbeer@users.noreply.github.com>
License-Expression: MIT
License-File: LICENSE
Keywords: harlequin,ide,sql,textual,tui
Classifier: Development Status :: 4 - Beta
Classifier: Operating System :: MacOS :: MacOS X
Classifier: Operating System :: Microsoft :: Windows
Classifier: Operating System :: POSIX :: Linux
Classifier: Programming Language :: Python :: 3.10
Classifier: Programming Language :: Python :: 3.11
Classifier: Programming Language :: Python :: 3.12
Classifier: Programming Language :: Python :: 3.13
Classifier: Programming Language :: Python :: 3.14
Requires-Python: >=3.10
Requires-Dist: click==8.1.8
Requires-Dist: duckdb>=0.8.0; python_version < '3.14'
Requires-Dist: duckdb>=1.4.2; python_version >= '3.14'
Requires-Dist: pandas>=2.3; python_version >= '3.14'
Requires-Dist: platformdirs<5.0,>=3.10
Requires-Dist: questionary==2.0.1
Requires-Dist: rich-click==1.8.5
Requires-Dist: shandy-sqlfmt>=0.28.2
Requires-Dist: textual-fastdatatable==0.14.0
Requires-Dist: textual-textarea==0.17.2
Requires-Dist: textual==6.4.0
Requires-Dist: tomlkit<0.14.0,>=0.12.5
Provides-Extra: adbc
Requires-Dist: harlequin-adbc; extra == 'adbc'
Provides-Extra: bigquery
Requires-Dist: harlequin-bigquery; extra == 'bigquery'
Provides-Extra: cassandra
Requires-Dist: harlequin-cassandra; extra == 'cassandra'
Provides-Extra: databricks
Requires-Dist: harlequin-databricks; extra == 'databricks'
Provides-Extra: mysql
Requires-Dist: harlequin-mysql; extra == 'mysql'
Provides-Extra: nebulagraph
Requires-Dist: harlequin-nebulagraph; extra == 'nebulagraph'
Provides-Extra: odbc
Requires-Dist: harlequin-odbc; extra == 'odbc'
Provides-Extra: postgres
Requires-Dist: harlequin-postgres; extra == 'postgres'
Provides-Extra: s3
Requires-Dist: boto3==1.34.22; extra == 's3'
Provides-Extra: trino
Requires-Dist: harlequin-trino; extra == 'trino'
